ZetcodeGuiJiaochengChuyiFix1/README.md
ZetcodeGuiJiaochengChuyiFix1/__init__.py
ZetcodeGuiJiaochengChuyiFix1/__main__.py
ZetcodeGuiJiaochengChuyiFix1/file.epub
ZetcodeGuiJiaochengChuyiFix1/index.html
ZetcodeGuiJiaochengChuyiFix1/css/__init__.py
ZetcodeGuiJiaochengChuyiFix1/css/annotations.css
ZetcodeGuiJiaochengChuyiFix1/css/main.css
ZetcodeGuiJiaochengChuyiFix1/css/normalize.css
ZetcodeGuiJiaochengChuyiFix1/css/popup.css
ZetcodeGuiJiaochengChuyiFix1/font/__init__.py
ZetcodeGuiJiaochengChuyiFix1/font/fontello.eot
ZetcodeGuiJiaochengChuyiFix1/font/fontello.svg
ZetcodeGuiJiaochengChuyiFix1/font/fontello.ttf
ZetcodeGuiJiaochengChuyiFix1/font/fontello.woff
ZetcodeGuiJiaochengChuyiFix1/img/__init__.py
ZetcodeGuiJiaochengChuyiFix1/img/annotator-glyph-sprite.png
ZetcodeGuiJiaochengChuyiFix1/img/annotator-icon-sprite.png
ZetcodeGuiJiaochengChuyiFix1/img/apple-touch-icon.png
ZetcodeGuiJiaochengChuyiFix1/img/cancelfullscreen.png
ZetcodeGuiJiaochengChuyiFix1/img/close.png
ZetcodeGuiJiaochengChuyiFix1/img/fullscreen.png
ZetcodeGuiJiaochengChuyiFix1/img/loader.gif
ZetcodeGuiJiaochengChuyiFix1/img/menu-icon.png
ZetcodeGuiJiaochengChuyiFix1/img/save.png
ZetcodeGuiJiaochengChuyiFix1/img/saved.png
ZetcodeGuiJiaochengChuyiFix1/img/settings-s.png
ZetcodeGuiJiaochengChuyiFix1/img/settings.png
ZetcodeGuiJiaochengChuyiFix1/img/star.png
ZetcodeGuiJiaochengChuyiFix1/js/__init__.py
ZetcodeGuiJiaochengChuyiFix1/js/epub.js
ZetcodeGuiJiaochengChuyiFix1/js/epub.min.js
ZetcodeGuiJiaochengChuyiFix1/js/epub.min.map
ZetcodeGuiJiaochengChuyiFix1/js/hooks.min.js
ZetcodeGuiJiaochengChuyiFix1/js/hooks.min.map
ZetcodeGuiJiaochengChuyiFix1/js/reader.js
ZetcodeGuiJiaochengChuyiFix1/js/reader.js.map
ZetcodeGuiJiaochengChuyiFix1/js/reader.min.js
ZetcodeGuiJiaochengChuyiFix1/js/reader.min.map
ZetcodeGuiJiaochengChuyiFix1/js/hooks/__init__.py
ZetcodeGuiJiaochengChuyiFix1/js/hooks/extensions/__init__.py
ZetcodeGuiJiaochengChuyiFix1/js/hooks/extensions/highlight.js
zetcode_gui_jiaocheng_chuyi_fix1-2025.3.24.1.dist-info/METADATA
zetcode_gui_jiaocheng_chuyi_fix1-2025.3.24.1.dist-info/WHEEL
zetcode_gui_jiaocheng_chuyi_fix1-2025.3.24.1.dist-info/entry_points.txt
zetcode_gui_jiaocheng_chuyi_fix1-2025.3.24.1.dist-info/top_level.txt
zetcode_gui_jiaocheng_chuyi_fix1-2025.3.24.1.dist-info/RECORD
